{"otherData": {},"traceEvents":[{"cat":"function","dur":4430,"name":"void __cdecl Vortex::OpenGLContext::Init(void)","ph":"X","pid":0,"tid":3374142169,"ts":170577939352},{"cat":"function","dur":34,"name":"void __cdecl Vortex::WindowsWindow::SetVSync(bool)","ph":"X","pid":0,"tid":3374142169,"ts":170577943953},{"cat":"function","dur":213639,"name":"void __cdecl Vortex::WindowsWindow::Init(const struct Vortex::WindowProps &)","ph":"X","pid":0,"tid":3374142169,"ts":170577730407},{"cat":"function","dur":213673,"name":"__cdecl Vortex::WindowsWindow::WindowsWindow(const struct Vortex::WindowProps &)","ph":"X","pid":0,"tid":3374142169,"ts":170577730407},{"cat":"function","dur":6,"name":"void __cdecl Vortex::OpenGLRendererAPI::Init(void)","ph":"X","pid":0,"tid":3374142169,"ts":170577944132},{"cat":"function","dur":21,"name":"__cdecl Vortex::OpenGLVertexArray::OpenGLVertexArray(void)","ph":"X","pid":0,"tid":3374142169,"ts":170577944190},{"cat":"function","dur":15,"name":"__cdecl Vortex::OpenGLVertexBuffer::OpenGLVertexBuffer(float *,unsigned int)","ph":"X","pid":0,"tid":3374142169,"ts":170577944259},{"cat":"function","dur":0,"name":"void __cdecl Vortex::OpenGLVertexBuffer::Bind(void) const","ph":"X","pid":0,"tid":3374142169,"ts":170577944693},{"cat":"function","dur":422,"name":"void __cdecl Vortex::OpenGLVertexArray::AddVertexBuffer(const class std::shared_ptr<class Vortex::VertexBuffer> &)","ph":"X","pid":0,"tid":3374142169,"ts":170577944330},{"cat":"function","dur":69,"name":"__cdecl Vortex::OpenGLIndexBuffer::OpenGLIndexBuffer(unsigned int *,unsigned int)","ph":"X","pid":0,"tid":3374142169,"ts":170577944790},{"cat":"function","dur":0,"name":"void __cdecl Vortex::OpenGLIndexBuffer::Bind(void) const","ph":"X","pid":0,"tid":3374142169,"ts":170577944960},{"cat":"function","dur":41,"name":"void __cdecl Vortex::OpenGLVertexArray::SetIndexBuffer(const class std::shared_ptr<class Vortex::IndexBuffer> &)","ph":"X","pid":0,"tid":3374142169,"ts":170577944958},{"cat":"function","dur":31,"name":"__cdecl Vortex::OpenGLTexture2D::OpenGLTexture2D(unsigned int &,unsigned int &)","ph":"X","pid":0,"tid":3374142169,"ts":170577945042},{"cat":"function","dur":10,"name":"void __cdecl Vortex::OpenGLTexture2D::SetData(void *,unsigned int)","ph":"X","pid":0,"tid":3374142169,"ts":170577945118},{"cat":"function","dur":139,"name":"class std::basic_string<char,struct std::char_traits<char>,class std::allocator<char> > __cdecl Vortex::OpenGLShader::ReadFile(const class std::basic_string<char,struct std::char_traits<char>,class std::allocator<char> > &)","ph":"X","pid":0,"tid":3374142169,"ts":170577945189},{"cat":"function","dur":40,"name":"class std::unordered_map<unsigned int,class std::basic_string<char,struct std::char_traits<char>,class std::allocator<char> >,struct std::hash<unsigned int>,struct std::equal_to<unsigned int>,class std::allocator<struct std::pair<unsigned int const ,class std::basic_string<char,struct std::char_traits<char>,class std::allocator<char> > > > > __cdecl Vortex::OpenGLShader::Preprocess(const class std::basic_string<char,struct std::char_traits<char>,class std::allocator<char> > &)","ph":"X","pid":0,"tid":3374142169,"ts":170577945370},{"cat":"function","dur":740,"name":"void __cdecl Vortex::OpenGLShader::Compile(const class std::unordered_map<unsigned int,class std::basic_string<char,struct std::char_traits<char>,class std::allocator<char> >,struct std::hash<unsigned int>,struct std::equal_to<unsigned int>,class std::allocator<struct std::pair<unsigned int const ,class std::basic_string<char,struct std::char_traits<char>,class std::allocator<char> > > > > &)","ph":"X","pid":0,"tid":3374142169,"ts":170577945444},{"cat":"function","dur":1089,"name":"__cdecl Vortex::OpenGLShader::OpenGLShader(const class std::basic_string<char,struct std::char_traits<char>,class std::allocator<char> > &)","ph":"X","pid":0,"tid":3374142169,"ts":170577945187},{"cat":"function","dur":4,"name":"void __cdecl Vortex::OpenGLShader::Bind(void) const","ph":"X","pid":0,"tid":3374142169,"ts":170577946322},{"cat":"function","dur":31,"name":"void __cdecl Vortex::OpenGLShader::SetInt(const class std::basic_string<char,struct std::char_traits<char>,class std::allocator<char> > &,const int)","ph":"X","pid":0,"tid":3374142169,"ts":170577946365},{"cat":"function","dur":2333,"name":"void __cdecl Vortex::Renderer2D::Init(void)","ph":"X","pid":0,"tid":3374142169,"ts":170577944179},{"cat":"function","dur":2415,"name":"void __cdecl Vortex::Renderer::Init(void)","ph":"X","pid":0,"tid":3374142169,"ts":170577944131},{"cat":"function","dur":835,"name":"void __cdecl Vortex::ImGuiLayer::OnAttach(void)","ph":"X","pid":0,"tid":3374142169,"ts":170577946584},{"cat":"function","dur":893,"name":"void __cdecl Vortex::Application::PushOverlay(class Vortex::Layer *)","ph":"X","pid":0,"tid":3374142169,"ts":170577946581},{"cat":"function","dur":217120,"name":"__cdecl Vortex::Application::Application(void)","ph":"X","pid":0,"tid":3374142169,"ts":170577730395},{"cat":"function","dur":4,"name":"__cdecl Vortex::OrthographicCamera::OrthographicCamera(float,float,float,float)","ph":"X","pid":0,"tid":3374142169,"ts":170577947566},{"cat":"function","dur":211,"name":"stbi_load - OpenGLTexture2D::OpenGLTexture2D(const std::string& path)","ph":"X","pid":0,"tid":3374142169,"ts":170577947626},{"cat":"function","dur":285,"name":"__cdecl Vortex::OpenGLTexture2D::OpenGLTexture2D(const class std::basic_string<char,struct std::char_traits<char>,class std::allocator<char> > &)","ph":"X","pid":0,"tid":3374142169,"ts":170577947623},{"cat":"function","dur":343,"name":"void __cdecl Vortex::Application::PushLayer(class Vortex::Layer *)","ph":"X","pid":0,"tid":3374142169,"ts":170577947612}]}